wireguard/__init__.py
wireguard/wireguard.py
wireguard_lib-0.1.10.dist-info/LICENSE
wireguard_lib-0.1.10.dist-info/METADATA
wireguard_lib-0.1.10.dist-info/WHEEL
wireguard_lib-0.1.10.dist-info/top_level.txt
wireguard_lib-0.1.10.dist-info/RECORD
