Metadata-Version: 2.1
Name: wireguard-lib
Version: 0.1.10
Summary: Библиотека для работы с wireguard
Home-page: https://github.com/viktor-gorinskiy/wireguard-lib
Author: Viktor Gorinskiy
Author-email: viktor@gorinskiy.ru
License: UNKNOWN
Platform: UNKNOWN
Classifier: Programming Language :: Python :: 3.6
Classifier: License :: OSI Approved :: MIT License
Classifier: Operating System :: OS Independent
Requires-Python: >=3.6
Requires-Dist: qrcode (==7.3.1)
